sinpol/__init__.py
sinpol/crystaldata.py
sinpol/diffmodels.py
sinpol/sampledata.py
sinpol/scatteringcal.py
sinpol/stressstrainmodels.py
sinpol_transmission-1.0.dist-info/METADATA
sinpol_transmission-1.0.dist-info/WHEEL
sinpol_transmission-1.0.dist-info/entry_points.txt
sinpol_transmission-1.0.dist-info/top_level.txt
sinpol_transmission-1.0.dist-info/RECORD
