Metadata-Version: 2.4
Name: sinpol-transmission
Version: 1.0
Summary: Single crystal to polycrystal neutron trasnmission and diffraction simulation engine
Home-page: https://github.com/lldj15/Sinpol
Author: Luc Dessieux
Author-email: Luc Dessieux <Dessieuxll@ornl.gov>
Project-URL: Homepage, https://github.com/lldj15/sinpol
Keywords: neutron transmission simulation,neutron Bragg edge simulation,neutron transmission single crystal simulation
Classifier: Development Status :: 3 - Alpha
Classifier: License :: OSI Approved :: BSD License
Classifier: Topic :: Scientific/Engineering :: Physics
Classifier: Intended Audience :: Developers
Classifier: Programming Language :: Python :: 3.9
Classifier: Programming Language :: Python :: 3.10
Classifier: Programming Language :: Python :: 3.11
Requires-Python: >=3.10
Requires-Dist: periodictable
Requires-Dist: mpmath
Requires-Dist: elementy
Requires-Dist: scipy
Requires-Dist: numba
Requires-Dist: numba-mpi
Requires-Dist: ase
Requires-Dist: matlabengine
Provides-Extra: dev
Requires-Dist: black; extra == "dev"
Requires-Dist: bumpver; extra == "dev"
Requires-Dist: isort; extra == "dev"
Requires-Dist: pip-tools; extra == "dev"
Requires-Dist: pytest; extra == "dev"
Dynamic: author
Dynamic: home-page
